[{"id":162,"name":"Chicken Tossed Nachos","category":"Nachos (Non-Veg)","type":"nonveg","img":"/Images/Chicken-Tossed-Nachos.webp","description":"Nachos tossed with chicken","variants":[{"size":"Regular","price":170}]},{"id":163,"name":"Salami Ribbon Nachos","category":"Nachos (Non-Veg)","type":"nonveg","img":"/Images/Salami-Ribbon-Nachos.webp","description":"Nachos topped with chicken salami ribbons","variants":[{"size":"Regular","price":190}]},{"id":164,"name":"Ham & Mutton Chops Nachos","category":"Nachos (Non-Veg)","type":"nonveg","img":"/Images/Ham-Mutton-Chops-Nachos.webp","description":"Nachos topped with ham & mutton pieces","variants":[{"size":"Regular","price":210}]},{"id":165,"name":"Baked Pepperoni & Chicken Nachos","category":"Nachos (Non-Veg)","type":"nonveg","img":"/Images/Baked-Pepperoni-Chicken-Nachos.webp","description":"Baked nachos with pepperoni & chicken","variants":[{"size":"Regular","price":230}]},{"id":166,"name":"Rifle-18 (One Pot Chicken Baked Nachos)","category":"Nachos (Non-Veg)","type":"nonveg","img":"/Images/Rifle-18-Chicken-Baked-Nachos.webp","description":"One-pot baked chicken nachos","variants":[{"size":"Regular","price":270}]}]